src/__init__.py
src/http_request_manager.py
src/model.py
src/qweather.py
qweather_api-0.1.1.dist-info/LICENSE
qweather_api-0.1.1.dist-info/METADATA
qweather_api-0.1.1.dist-info/WHEEL
qweather_api-0.1.1.dist-info/top_level.txt
qweather_api-0.1.1.dist-info/RECORD
