Metadata-Version: 2.1
Name: qweather-api
Version: 0.1.1
Summary: QWeatherPython API
Home-page: https://github.com/shaun17/qweather-api.git
Author: wenren
Author-email: shaun.17g@gmail.com
Classifier: Programming Language :: Python :: 3
Classifier: License :: OSI Approved :: MIT License
Classifier: Operating System :: OS Independent
Requires-Python: >=3.6
License-File: LICENSE
Requires-Dist: requests
